{
  "pro_id": "PRO-094",
  "student_id": "STU-2019-1194",
  "pro_year": "2019",
  "pro_course_duration": "4",
  "pro_course_spec": "Algorithms and software specialisation",
  "pro_aos": "ALGSFTWR01",
  "pro_creds_total": "192",
  "pro_status": "graduated",
  "noise_type": ["mid_degree_specialisation_change"],
  "noise_notes": "Started in Data science specialisation (Y1-Y2S1, Sem1 2019 to Sem1 2020); changed to Algorithms and software after Y2S1 (Sem1 2020); FIT2179 (DS unit) credited as elective; FIT2099 taken as catch-up in Y2S2; FIT2109 shifted to Y3S1 to accommodate catch-up; completed Sem2 2022",
  "semesters": [
    {
      "year": 1, "semester": "First", "calendar_year": "2019",
      "slots": [
        { "slot": 1, "unit_code": "FIT1053", "unit_name": "Introduction to programming (advanced)", "type": "required", "status": "passed" },
        { "slot": 2, "unit_code": "FIT1047", "unit_name": "Introduction to computer systems, networks and security", "type": "required", "status": "passed" },
        { "slot": 3, "unit_code": "FIT1058", "unit_name": "Foundations of computing", "type": "required", "status": "passed" },
        { "slot": 4, "unit_code": "FIT1006", "unit_name": "Business information analysis", "type": "elective", "status": "passed" }
      ]
    },
    {
      "year": 1, "semester": "Second", "calendar_year": "2019",
      "slots": [
        { "slot": 1, "unit_code": "FIT1054", "unit_name": "Fundamentals of algorithms (advanced)", "type": "required", "status": "passed" },
        { "slot": 2, "unit_code": "FIT1049", "unit_name": "IT professional practice", "type": "required", "status": "passed" },
        { "slot": 3, "unit_code": "FIT1043", "unit_name": "Introduction to data science", "type": "required", "status": "passed" },
        { "slot": 4, "unit_code": "FIT1060", "unit_name": "Human-centred design", "type": "elective", "status": "passed" }
      ]
    },
    {
      "year": 2, "semester": "First", "calendar_year": "2020",
      "slots": [
        { "slot": 1, "unit_code": "FIT2004", "unit_name": "Algorithms and data structures", "type": "required", "status": "passed" },
        { "slot": 2, "unit_code": "FIT2094", "unit_name": "Databases", "type": "required", "status": "passed" },
        { "slot": 3, "unit_code": "FIT2179", "unit_name": "Applied data analysis", "type": "elective", "status": "passed" },
        { "slot": 4, "unit_code": "FIT2083", "unit_name": "Innovation and research in computer science", "type": "required", "status": "passed" }
      ]
    },
    {
      "year": 2, "semester": "Second", "calendar_year": "2020",
      "slots": [
        { "slot": 1, "unit_code": "FIT2014", "unit_name": "Theory of computation", "type": "required", "status": "passed" },
        { "slot": 2, "unit_code": "FIT2099", "unit_name": "Object-oriented design and implementation", "type": "required", "status": "passed" },
        { "slot": 3, "unit_code": "FIT2102", "unit_name": "Programming paradigms", "type": "required", "status": "passed" },
        { "slot": 4, "unit_code": "FIT2082", "unit_name": "Computer science research project", "type": "required", "status": "passed" }
      ]
    },
    {
      "year": 3, "semester": "First", "calendar_year": "2021",
      "slots": [
        { "slot": 1, "unit_code": "FIT3161", "unit_name": "Computer science project 1", "type": "required", "status": "passed" },
        { "slot": 2, "unit_code": "FIT3146", "unit_name": "User experience research and design", "type": "level 3 discipline elective", "status": "passed" },
        { "slot": 3, "unit_code": "FIT3155", "unit_name": "Advanced data structures and algorithms", "type": "required", "status": "passed" },
        { "slot": 4, "unit_code": "FIT2109", "unit_name": "Computer science workshop", "type": "required", "status": "passed" }
      ]
    },
    {
      "year": 3, "semester": "Second", "calendar_year": "2021",
      "slots": [
        { "slot": 1, "unit_code": "FIT3162", "unit_name": "Computer science project 2", "type": "required", "status": "passed" },
        { "slot": 2, "unit_code": "FIT3143", "unit_name": "Parallel computing", "type": "required", "status": "passed" },
        { "slot": 3, "unit_code": "FIT3152", "unit_name": "Data analytics", "type": "elective", "status": "passed" },
        { "slot": 4, "unit_code": "FIT3031", "unit_name": "Network security", "type": "elective", "status": "passed" }
      ]
    },
    {
      "year": 4, "semester": "First", "calendar_year": "2022",
      "slots": [
        { "slot": 1, "unit_code": "FIT4441", "unit_name": "Honours thesis - part 1", "type": "required", "status": "passed" },
        { "slot": 2, "unit_code": "FIT4442", "unit_name": "Honours thesis - part 2", "type": "required", "status": "passed" },
        { "slot": 3, "unit_code": "FIT4001", "unit_name": "Special studies in engineering 1", "type": "level 4/5 faculty elective", "status": "passed" },
        { "slot": 4, "unit_code": "FIT3174", "unit_name": "Business information systems strategy and governance", "type": "elective", "status": "passed" }
      ]
    },
    {
      "year": 4, "semester": "Second", "calendar_year": "2022",
      "slots": [
        { "slot": 1, "unit_code": "FIT4443", "unit_name": "Honours thesis - part 3", "type": "required", "status": "passed" },
        { "slot": 2, "unit_code": "FIT4444", "unit_name": "Honours thesis - final", "type": "required", "status": "passed" },
        { "slot": 3, "unit_code": "FIT4002", "unit_name": "Special studies in engineering 2", "type": "level 4/5 faculty elective", "status": "passed" },
        { "slot": 4, "unit_code": "FIT3158", "unit_name": "Business decision modelling", "type": "elective", "status": "passed" }
      ]
    }
  ]
}
